PandoraCore/RAG/parser.py
PandoraCore/STT/whisper.py
PandoraCore/TTS/KokoroWrap.py
pandoracore-0.0.1.dist-info/METADATA
pandoracore-0.0.1.dist-info/WHEEL
pandoracore-0.0.1.dist-info/top_level.txt
pandoracore-0.0.1.dist-info/RECORD
