Metadata-Version: 2.4
Name: pandoraCore
Version: 0.0.1
Summary: The core toolbox for AI workflows: RAG, document processing, speech, and more.
Author-email: Yahir Luna <j.luna2016@hotmail.com>
